nonebot_plugin_phigros/__init__.py
nonebot_plugin_phigros/config.py
nonebot_plugin_phigros/simyou.ttf
nonebot_plugin_phigros-0.2.5.dist-info/METADATA
nonebot_plugin_phigros-0.2.5.dist-info/WHEEL
nonebot_plugin_phigros-0.2.5.dist-info/top_level.txt
nonebot_plugin_phigros-0.2.5.dist-info/RECORD
